MANIFEST.in
README.md
setup.py
demos/__init__.py
demos/__main__.py
demos/bmi.py
demos/bokeh_app.py
demos/chat_room.py
demos/chatgpt.py
demos/config.py
demos/doc_demo.py
demos/gomoku_game.py
demos/index.py
demos/input_usage.py
demos/markdown_previewer.py
demos/output_usage.py
demos/set_env_demo.py
demos/theme.py
demos/wordle.py
pywebio/__init__.py
pywebio/__version__.py
pywebio/exceptions.py
pywebio/input.py
pywebio/io_ctrl.py
pywebio/output.py
pywebio/pin.py
pywebio/utils.py
pywebio.egg-info/PKG-INFO
pywebio.egg-info/SOURCES.txt
pywebio.egg-info/dependency_links.txt
pywebio.egg-info/entry_points.txt
pywebio.egg-info/requires.txt
pywebio.egg-info/top_level.txt
pywebio/html/codemirror/active-line.js
pywebio/html/codemirror/addons.js
pywebio/html/codemirror/autorefresh.js
pywebio/html/codemirror/loadmode.js
pywebio/html/codemirror/matchbrackets.js
pywebio/html/codemirror/python.js
pywebio/html/css/app.css
pywebio/html/css/bootstrap-select.min.css
pywebio/html/css/codemirror.min.css
pywebio/html/css/markdown.min.css
pywebio/html/css/toastify.min.css
pywebio/html/css/bs-theme/dark.min.css
pywebio/html/css/bs-theme/default.min.css
pywebio/html/css/bs-theme/minty.min.css
pywebio/html/css/bs-theme/sketchy.min.css
pywebio/html/css/bs-theme/yeti.min.css
pywebio/html/image/apple-touch-icon.png
pywebio/html/image/favicon_closed_16.png
pywebio/html/image/favicon_closed_32.png
pywebio/html/image/favicon_open_16.png
pywebio/html/image/favicon_open_32.png
pywebio/html/js/FileSaver.min.js
pywebio/html/js/bootstrap-select.min.js
pywebio/html/js/bootstrap.min.js
pywebio/html/js/bs-custom-file-input.min.js
pywebio/html/js/codemirror.min.js
pywebio/html/js/jquery.min.js
pywebio/html/js/mustache.min.js
pywebio/html/js/popper.min.js
pywebio/html/js/prism.min.js
pywebio/html/js/purify.min.js
pywebio/html/js/pywebio.min.js
pywebio/html/js/require.min.js
pywebio/html/js/toastify.min.js
pywebio/platform/__init__.py
pywebio/platform/aiohttp.py
pywebio/platform/bokeh.py
pywebio/platform/django.py
pywebio/platform/fastapi.py
pywebio/platform/flask.py
pywebio/platform/page.py
pywebio/platform/path_deploy.py
pywebio/platform/remote_access.py
pywebio/platform/tornado.py
