Metadata-Version: 2.1
Name: pywebio
Version: 1.8.3
Summary: Write interactive web app in script way.
Home-page: https://pywebio.readthedocs.io
Author: WangWeimin
Author-email: wang0.618@qq.com
License: MIT
Project-URL: Documentation, https://pywebio.readthedocs.io
Project-URL: Source, https://github.com/wang0618/PyWebIO
Platform: UNKNOWN
Classifier: Programming Language :: Python :: 3
Classifier: Programming Language :: Python :: 3.5
Classifier: Programming Language :: Python :: 3.6
Classifier: Programming Language :: Python :: 3.7
Classifier: Programming Language :: Python :: 3.8
Requires-Python: >=3.5.2
Provides-Extra: flask
Provides-Extra: django
Provides-Extra: aiohttp
Provides-Extra: bokeh
Provides-Extra: doc
Provides-Extra: all
